openpmd_validator/__init__.py
openpmd_validator/check_h5.py
openpmd_validator/createExamples_h5.py
openPMD_validator-1.1.0.6.dist-info/LICENSE.txt
openPMD_validator-1.1.0.6.dist-info/METADATA
openPMD_validator-1.1.0.6.dist-info/WHEEL
openPMD_validator-1.1.0.6.dist-info/entry_points.txt
openPMD_validator-1.1.0.6.dist-info/top_level.txt
openPMD_validator-1.1.0.6.dist-info/RECORD
