Metadata-Version: 2.1
Name: openPMD-validator
Version: 1.1.0.6
Summary: Validator and examples for openPMD format
Home-page: https://github.com/openPMD/openPMD-validator
License: ISC
Classifier: Environment :: Console
Classifier: Intended Audience :: Science/Research
Classifier: License :: OSI Approved :: ISC License (ISCL)
Classifier: Operating System :: OS Independent
Classifier: Programming Language :: Python :: 2.7
Classifier: Programming Language :: Python :: 3
Classifier: Topic :: Scientific/Engineering :: Physics
License-File: LICENSE.txt
Requires-Dist: numpy (>=1.6.1)
Requires-Dist: python-dateutil (>=2.3.0)
Requires-Dist: h5py (>=2.0.0)
